oc_idmanager/__init__.py
oc_idmanager/base.py
oc_idmanager/doi.py
oc_idmanager/isbn.py
oc_idmanager/issn.py
oc_idmanager/orcid.py
oc_idmanager/pmcid.py
oc_idmanager/pmid.py
oc_idmanager/ror.py
oc_idmanager/support.py
oc_idmanager/url.py
oc_idmanager/viaf.py
oc_idmanager/wikidata.py
oc_idmanager/wikipedia.py
oc_idmanager-0.2.6.dist-info/LICENSE.md
oc_idmanager-0.2.6.dist-info/METADATA
oc_idmanager-0.2.6.dist-info/WHEEL
oc_idmanager-0.2.6.dist-info/RECORD
