Metadata-Version: 2.1
Name: oc-idmanager
Version: 0.2.6
Summary: This library allows validating identifiers with DOI, ISBN, ISSN, ORCID, PMCID, and PMID schemes
License: ISC
Author: Silvio Peroni
Author-email: essepuntato@gmail.com
Requires-Python: >=3.7.4,<4.0.0
Classifier: License :: OSI Approved
Classifier: Programming Language :: Python :: 3
Classifier: Programming Language :: Python :: 3.8
Classifier: Programming Language :: Python :: 3.9
Classifier: Programming Language :: Python :: 3.10
Classifier: Programming Language :: Python :: 3.11
Requires-Dist: beautifulsoup4 (>=4.11.1,<5.0.0)
Requires-Dist: lxml (>=4.9.1,<5.0.0)
Requires-Dist: oc-meta (==1.2.4)
Requires-Dist: requests (>=2.28.1,<3.0.0)
Requires-Dist: validators (>=0.20.0,<0.21.0)
